sf_gear-0.1.0.dist-info/licenses/LICENSE
sfgear/__init__.py
sfgear/utils.py
sfgear/cli/__init__.py
sfgear/cli/data.py
sfgear/cli/org.py
sf_gear-0.1.0.dist-info/METADATA
sf_gear-0.1.0.dist-info/WHEEL
sf_gear-0.1.0.dist-info/top_level.txt
sf_gear-0.1.0.dist-info/RECORD
