Metadata-Version: 2.4
Name: sf-gear
Version: 0.1.0
Summary: A Python library for Salesforce API and CLI integration
Author-email: Alexander Hooke <alexander.hooke@gmail.com>
License-Expression: MIT
Keywords: salesforce,api,cli,tooling
Classifier: Development Status :: 3 - Alpha
Classifier: Programming Language :: Python :: 3
Classifier: Programming Language :: Python :: 3.10
Classifier: Programming Language :: Python :: 3.11
Classifier: Programming Language :: Python :: 3.12
Classifier: Operating System :: OS Independent
Classifier: Intended Audience :: Developers
Classifier: Topic :: Software Development :: Libraries
Classifier: Topic :: Utilities
Requires-Python: >=3.10
License-File: LICENSE
Dynamic: license-file
